AlmaxClasses/Result.py
AlmaxClasses/__init__.py
AlmaxGraphics/FrameManager.py
AlmaxGraphics/__init__.py
AlmaxLogs/LoggerService.py
AlmaxLogs/__init__.py
AlmaxSystemManagment/CustomSubprocess.py
AlmaxSystemManagment/CustomThread.py
AlmaxSystemManagment/__init__.py
AlmaxUtils/FileSystem.py
AlmaxUtils/Generic.py
AlmaxUtils/PdfManager.py
AlmaxUtils/Time.py
AlmaxUtils/Xml.py
AlmaxUtils/__init__.py
almax_common-1.0.6.dist-info/METADATA
almax_common-1.0.6.dist-info/WHEEL
almax_common-1.0.6.dist-info/top_level.txt
almax_common-1.0.6.dist-info/RECORD
