Metadata-Version: 2.1
Name: almax_common
Version: 1.0.6
Summary: Library with my most used Classes and Methods
Author: AlMax98
Author-email: alihaider.maqsood@gmail.com
Requires-Dist: chardet ==5.2.0
Requires-Dist: codicefiscale ==0.9
Requires-Dist: colorama ==0.4.6
Requires-Dist: iniconfig ==2.0.0
Requires-Dist: packaging ==24.0
Requires-Dist: pillow ==10.3.0
Requires-Dist: pluggy ==1.5.0
Requires-Dist: pypdf ==4.2.0
Requires-Dist: pytest ==8.2.1
Requires-Dist: reportlab ==4.2.0
Requires-Dist: setuptools ==70.0.0
